setup.py
rl_mle_distributions/Binomialdistribution.py
rl_mle_distributions/Gaussiandistribution.py
rl_mle_distributions/Generaldistribution.py
rl_mle_distributions/__init__.py
rl_mle_distributions.egg-info/PKG-INFO
rl_mle_distributions.egg-info/SOURCES.txt
rl_mle_distributions.egg-info/dependency_links.txt
rl_mle_distributions.egg-info/not-zip-safe
rl_mle_distributions.egg-info/top_level.txt